obsinfo/__init__.py
obsinfo/version.py
obsinfo/_examples/.DS_Store
obsinfo/_examples/instrumentation_files/.DS_Store
obsinfo/_examples/instrumentation_files/README.md
obsinfo/_examples/instrumentation_files/datalogger_bases/.DS_Store
obsinfo/_examples/instrumentation_files/datalogger_bases/EXAMPLE.datalogger_base.yaml
obsinfo/_examples/instrumentation_files/datalogger_bases/stage_bases/.DS_Store
obsinfo/_examples/instrumentation_files/datalogger_bases/stage_bases/EXAMPLE_FIR1.stage_base.yaml
obsinfo/_examples/instrumentation_files/datalogger_bases/stage_bases/EXAMPLE_FIR2.stage_base.yaml
obsinfo/_examples/instrumentation_files/datalogger_bases/stage_bases/EXAMPLE_FIR3.stage_base.yaml
obsinfo/_examples/instrumentation_files/datalogger_bases/stage_bases/filters/.DS_Store
obsinfo/_examples/instrumentation_files/datalogger_bases/stage_bases/filters/EXAMPLE_FIR3.filter.yaml
obsinfo/_examples/instrumentation_files/instrumentation_bases/.DS_Store
obsinfo/_examples/instrumentation_files/instrumentation_bases/EXAMPLE.instrumentation_base.yaml
obsinfo/_examples/instrumentation_files/instrumentation_bases/EXAMPLE_CBBOBS.instrumentation_base.yaml
obsinfo/_examples/instrumentation_files/instrumentation_bases/EXAMPLE_noconfigs.instrumentation_base.yaml
obsinfo/_examples/instrumentation_files/location_bases/.DS_Store
obsinfo/_examples/instrumentation_files/location_bases/EXAMPLE.location_base.yaml
obsinfo/_examples/instrumentation_files/networks/.DS_Store
obsinfo/_examples/instrumentation_files/networks/EXAMPLE.network.yaml
obsinfo/_examples/instrumentation_files/operators/.DS_Store
obsinfo/_examples/instrumentation_files/operators/EXAMPLE.operator.yaml
obsinfo/_examples/instrumentation_files/persons/.DS_Store
obsinfo/_examples/instrumentation_files/persons/EXAMPLE.person.yaml
obsinfo/_examples/instrumentation_files/preamplifier_bases/.DS_Store
obsinfo/_examples/instrumentation_files/preamplifier_bases/EXAMPLE_BBOBS.preamplifier_base.yaml
obsinfo-1.0.1.dist-info/LICENSE.txt
obsinfo-1.0.1.dist-info/METADATA
obsinfo-1.0.1.dist-info/WHEEL
obsinfo-1.0.1.dist-info/entry_points.txt
obsinfo-1.0.1.dist-info/top_level.txt
obsinfo-1.0.1.dist-info/RECORD
