Metadata-Version: 2.2
Name: obsinfo
Version: 1.0.1
Summary: Tools for documenting ocean bottom seismometer experiments and creating metadata
Home-page: https://gitlab.com/resif/smm/obsinfo
Author: Wayne Crawford
Author-email: crawford@ipgp.fr
Keywords: seismology OBS
Classifier: Development Status :: 4 - Beta
Classifier: Environment :: Console
Classifier: Intended Audience :: Science/Research
Classifier: Intended Audience :: Developers
Classifier: License :: OSI Approved :: GNU General Public License v3 (GPLv3)
Classifier: Natural Language :: English
Classifier: Operating System :: OS Independent
Classifier: Programming Language :: Python :: 3
Classifier: Programming Language :: Python :: 3.6
Classifier: Topic :: Scientific/Engineering
Classifier: Topic :: Scientific/Engineering :: Physics
Requires-Python: >=3.9
License-File: LICENSE.txt
Requires-Dist: numpy>=1.26
Requires-Dist: obspy>=1.4
Requires-Dist: pyyaml>=6.0
Requires-Dist: jsonschema<4,>=3.2
Requires-Dist: python-gitlab>=5.0
Requires-Dist: jsonref>=1.1
Requires-Dist: cartopy>=0.23.0
Requires-Dist: requests>=2.28
Dynamic: author
Dynamic: author-email
Dynamic: classifier
Dynamic: description
Dynamic: description-content-type
Dynamic: home-page
Dynamic: keywords
Dynamic: requires-dist
Dynamic: requires-python
Dynamic: summary
